clean_directories-1.1.0.dist-info/RECORD
clean_directories-1.1.0.dist-info/top_level.txt
clean_directories-1.1.0.dist-info/entry_points.txt
clean_directories-1.1.0.dist-info/DESCRIPTION.rst
clean_directories-1.1.0.dist-info/WHEEL
clean_directories-1.1.0.dist-info/metadata.json
clean_directories-1.1.0.dist-info/METADATA
clean_directories/files.py
clean_directories/__init__.py
bin/cleaner.py
bin/__init__.py
bin/clean.py
