Metadata-Version: 2.0
Name: clean-directories
Version: 1.1.0
Summary: A script to clean your directories
Home-page: https://github.com/Shir0kamii/clean
Author: shir0kamii
Author-email: Shir0kamii@prologin.org
License: MIT
Keywords: script clean directories
Platform: UNKNOWN
Classifier: Development Status :: 3 - Alpha
Classifier: Intended Audience :: Developers
Classifier: License :: OSI Approved :: MIT License
Classifier: Programming Language :: Python :: 3
Classifier: Programming Language :: Python :: 3.2
Classifier: Programming Language :: Python :: 3.3
Classifier: Programming Language :: Python :: 3.4
Requires-Dist: clize
Requires-Dist: scandir
